{
  "muscles": [
    "Hele Core-muskulaturen",
    "Lats",
    "Serratus Anterior"
  ],
  "benefits": [
    "En af de mest effektive øvelser for 'anti-extension' styrke.",
    "Træner coren til at stabilisere rygsøjlen under ekstremt stræk.",
    "Giver en enorm styrke-overførsel til andre tunge løft."
  ],
  "setup": [
    "Knæl på en blød måtte og tag fat i håndtagene på ab-wheelet.",
    "Start med hjulet direkte under dine skuldre.",
    "Lav en 'hollow body' position med en let runding i øvre ryg."
  ],
  "execution": [
    "Rul hjulet kontrolleret fremad så langt du kan uden at miste spændingen.",
    "Hold din core stram og undgå at lade lænden svaje (arch).",
    "Træk hjulet tilbage til startpositionen ved at bruge maven, ikke armene.",
    "Tip: Jo længere du ruller ud, jo tungere bliver øvelsen."
  ],
  "title": "Ab Wheel",
  "focusPoints": [],
  "tempo": [
    0,
    0,
    0,
    0
  ]
}